Q3.v
module Multiplier (
    input [3:0] Mul_In1, Mul_In2,
    output [7:0] Mul_Out
);
    assign Mul_Out = Mul_In1 * Mul_In2;
endmodule

module Adder (
    input [10:0] Add_In1, Add_In2,
    output [10:0] Add_Out
);
    assign Add_Out = Add_In1 + Add_In2;
endmodule

module In_Mux (
    input [3:0] In_0, In_1, In_2, In_3, In_4,
    input [2:0] sel,
    output reg [3:0] Out
);
    always @*
    case (sel)
        3'b000: Out <= In_0;
        3'b001: Out <= In_1;
        3'b010: Out <= In_2;
        3'b011: Out <= In_3;
        3'b100: Out <= In_4;
        default: Out <= 0;
    endcase;
endmodule

module OutMux (
    input [10:0] In_0, In_1, In_2, In_3, In_4,
    input [2:0] sel,
    output reg [10:0] Out
);
    always @*
    case (sel)
        3'b000: Out = In_0;
        3'b001: Out = In_1;
        3'b010: Out = In_2;
        3'b011: Out = In_3;
        3'b100: Out = In_4;
        default: Out = 11'b0;
    endcase;
endmodule

module Q3 (
    input clk,
    input [3:0] x_0, x_1, x_2, x_3, x_4, x_5, x_6, x_7, x_8, x_9, h_0, h_1, h_2, h_3, h_4, h_5, h_6, h_7, h_8, h_9,
    output reg [10:0] out
);
    reg [3:0] counter = 4'b0000;
    reg [2:0] sel_i, sel_j;
    reg [10:0] a0, a1, a2, a3, a4, a5, a6, a7;

    wire [3:0] MulIn1, MulIn2, MulIn3, MulIn4;
    wire [7:0] MulOut1, MulOut2;
    wire [10:0] AddIn1, AddIn2, AddOut;

    In_Mux I1(x_0, x_2, x_4, x_6, x_8, sel_i, MulIn1);
    In_Mux I2(h_0, h_2, h_4, h_6, h_8, sel_i, MulIn2);

    In_Mux I3(x_1, x_3, x_5, x_7, x_9, sel_i, MulIn3);
    In_Mux I4(h_1, h_3, h_5, h_7, h_9, sel_i, MulIn4);

    Multiplier M1(MulIn1, MulIn2, MulOut1);
    Multiplier M2(MulIn3, MulIn4, MulOut2);

    OutMux O1({3'b000,MulOut1}, a0, a1, a2, a3, sel_j, AddIn1);
    OutMux O2({3'b000,MulOut2}, a4, a5, a6, a7, sel_j, AddIn2);

    Adder A1(AddIn1, AddIn2, AddOut);

    always @(posedge clk) begin
        counter <= (counter == 4'b1000) ? 4'b0000 : counter + 1;
        sel_i <= (counter == 4'b1000) ? 3'b000 : sel_i + 1;
        sel_j <= (counter < 4'b0100 || counter == 4'b1000) ? 3'b000 : sel_j + 1;
    end

    always @(x_0, x_1, x_2, x_3, x_4, x_5, x_6, x_7, x_8, x_9, h_0, h_1, h_2, h_3, h_4, h_5, h_6, h_7, h_8, h_9) begin
        counter<=4'b0000;
        sel_i <= 3'b000;
        sel_j <= 3'b000;
        out <= 0;
    end

    always @* begin
        case (counter)
            4'd0: a0 <= AddOut;
            4'd1: a1 <= AddOut;
            4'd2: a2 <= AddOut;
            4'd3: a3 <= AddOut;
            4'd4: a4 <= AddOut;
            4'd5: a5 <= AddOut;
            4'd6: a6 <= AddOut;
            4'd7: a7 <= AddOut;
            4'd8: out <= AddOut;
        endcase
    end
endmodule

Q3_tb.v
`timescale 1ns/1ns
`include "Q3.v"

module Q3_tb;

  // Declaring Port parameters for testbench
  reg [3:0] x_0, x_1, x_2, x_3, x_4, x_5, x_6, x_7, x_8, x_9, h_0, h_1, h_2, h_3, h_4, h_5, h_6, h_7, h_8, h_9;
  reg clk = 1'b0;
  wire [10:0] Output;

  // Clock pulse generation
  always #1 clk = ~clk;

  // Instantiate the DUT (Design Under Test)
  Q3 uut (
    .out(Output),
    .clk(clk),
    .x_0(x_0), .x_1(x_1), .x_2(x_2), .x_3(x_3), .x_4(x_4), .x_5(x_5), .x_6(x_6), .x_7(x_7), .x_8(x_8), .x_9(x_9),
    .h_0(h_0), .h_1(h_1), .h_2(h_2), .h_3(h_3), .h_4(h_4), .h_5(h_5), .h_6(h_6), .h_7(h_7), .h_8(h_8), .h_9(h_9)
  );

  // Declaring variables for testbench
  integer testcases, expected_out;

  // Monitoring the input values & Output
  initial begin
    $monitor($time, "x_0=%d x_1=%d x_2=%d x_3=%d x_4=%d x_5=%d x_6=%d x_7=%d x_8=%d x_9=%d h_0=%d h_1=%d h_2=%d h_3=%d h_4=%d h_5=%d h_6=%d h_7=%d h_8=%d h_9=%d Output=%d expected=%d",x_0, x_1, x_2, x_3, x_4, x_5, x_6, x_7, x_8, x_9, h_0, h_1, h_2, h_3, h_4, h_5, h_6, h_7, h_8, h_9, Output, expected_out);

    // Dumping waveform to VCD file
    $dumpfile("Q3.vcd");
    $dumpvars;

    // Finish simulation after 1100 time units
    #200 $finish;
  end

  // Running testcases
  initial begin
    // Initialize expected_out
    expected_out = x_0 * h_0 + x_1 * h_1 + x_2 * h_2 + x_3 * h_3 + x_4 * h_4 + x_5 * h_5 + x_6 * h_6 + x_7 * h_7 + x_8 * h_8 + x_9 * h_9;

    // Loop for 10 testcases
    for (testcases = 0; testcases < 10; testcases++) begin
      // Assign random values to inputs
      x_0 = $random; x_1 = $random; x_2 = $random; x_3 = $random; x_4 = $random;
      x_5 = $random; x_6 = $random; x_7 = $random; x_8 = $random; x_9 = $random;
      h_0 = $random; h_1 = $random; h_2 = $random; h_3 = $random; h_4 = $random;
      h_5 = $random; h_6 = $random; h_7 = $random; h_8 = $random; h_9 = $random;

      // Calculate expected_out for comparison
      expected_out = x_0 * h_0 + x_1 * h_1 + x_2 * h_2 + x_3 * h_3 + x_4 * h_4 + x_5 * h_5 + x_6 * h_6 + x_7 * h_7 + x_8 * h_8 + x_9 * h_9;
      #20;
    end
  end
endmodule

Q3.vcd
$date
	Sun Feb 04 22:11:55 2024
$end
$version
	Icarus Verilog
$end
$timescale
	1ns
$end
$scope module Q3_tb $end
$var wire 11 ! Output [10:0] $end
$var reg 1 " clk $end
$var reg 4 # h_0 [3:0] $end
$var reg 4 $ h_1 [3:0] $end
$var reg 4 % h_2 [3:0] $end
$var reg 4 & h_3 [3:0] $end
$var reg 4 ' h_4 [3:0] $end
$var reg 4 ( h_5 [3:0] $end
$var reg 4 ) h_6 [3:0] $end
$var reg 4 * h_7 [3:0] $end
$var reg 4 + h_8 [3:0] $end
$var reg 4 , h_9 [3:0] $end
$var reg 4 - x_0 [3:0] $end
$var reg 4 . x_1 [3:0] $end
$var reg 4 / x_2 [3:0] $end
$var reg 4 0 x_3 [3:0] $end
$var reg 4 1 x_4 [3:0] $end
$var reg 4 2 x_5 [3:0] $end
$var reg 4 3 x_6 [3:0] $end
$var reg 4 4 x_7 [3:0] $end
$var reg 4 5 x_8 [3:0] $end
$var reg 4 6 x_9 [3:0] $end
$var integer 32 7 expected_out [31:0] $end
$var integer 32 8 testcases [31:0] $end
$scope module uut $end
$var wire 1 " clk $end
$var wire 4 9 h_0 [3:0] $end
$var wire 4 : h_1 [3:0] $end
$var wire 4 ; h_2 [3:0] $end
$var wire 4 < h_3 [3:0] $end
$var wire 4 = h_4 [3:0] $end
$var wire 4 > h_5 [3:0] $end
$var wire 4 ? h_6 [3:0] $end
$var wire 4 @ h_7 [3:0] $end
$var wire 4 A h_8 [3:0] $end
$var wire 4 B h_9 [3:0] $end
$var wire 4 C x_0 [3:0] $end
$var wire 4 D x_1 [3:0] $end
$var wire 4 E x_2 [3:0] $end
$var wire 4 F x_3 [3:0] $end
$var wire 4 G x_4 [3:0] $end
$var wire 4 H x_5 [3:0] $end
$var wire 4 I x_6 [3:0] $end
$var wire 4 J x_7 [3:0] $end
$var wire 4 K x_8 [3:0] $end
$var wire 4 L x_9 [3:0] $end
$var wire 8 M MulOut2 [7:0] $end
$var wire 8 N MulOut1 [7:0] $end
$var wire 4 O MulIn4 [3:0] $end
$var wire 4 P MulIn3 [3:0] $end
$var wire 4 Q MulIn2 [3:0] $end
$var wire 4 R MulIn1 [3:0] $end
$var wire 11 S AddOut [10:0] $end
$var wire 11 T AddIn2 [10:0] $end
$var wire 11 U AddIn1 [10:0] $end
$var reg 11 V a0 [10:0] $end
$var reg 11 W a1 [10:0] $end
$var reg 11 X a2 [10:0] $end
$var reg 11 Y a3 [10:0] $end
$var reg 11 Z a4 [10:0] $end
$var reg 11 [ a5 [10:0] $end
$var reg 11 \ a6 [10:0] $end
$var reg 11 ] a7 [10:0] $end
$var reg 4 ^ counter [3:0] $end
$var reg 11 _ out [10:0] $end
$var reg 3 ` sel_i [2:0] $end
$var reg 3 a sel_j [2:0] $end
$scope module A1 $end
$var wire 11 b Add_Out [10:0] $end
$var wire 11 c Add_In2 [10:0] $end
$var wire 11 d Add_In1 [10:0] $end
$upscope $end
$scope module I1 $end
$var wire 4 e In_0 [3:0] $end
$var wire 4 f In_1 [3:0] $end
$var wire 4 g In_2 [3:0] $end
$var wire 4 h In_3 [3:0] $end
$var wire 4 i In_4 [3:0] $end
$var wire 3 j sel [2:0] $end
$var reg 4 k Out [3:0] $end
$upscope $end
$scope module I2 $end
$var wire 4 l In_0 [3:0] $end
$var wire 4 m In_1 [3:0] $end
$var wire 4 n In_2 [3:0] $end
$var wire 4 o In_3 [3:0] $end
$var wire 4 p In_4 [3:0] $end
$var wire 3 q sel [2:0] $end
$var reg 4 r Out [3:0] $end
$upscope $end
$scope module I3 $end
$var wire 4 s In_0 [3:0] $end
$var wire 4 t In_1 [3:0] $end
$var wire 4 u In_2 [3:0] $end
$var wire 4 v In_3 [3:0] $end
$var wire 4 w In_4 [3:0] $end
$var wire 3 x sel [2:0] $end
$var reg 4 y Out [3:0] $end
$upscope $end
$scope module I4 $end
$var wire 4 z In_0 [3:0] $end
$var wire 4 { In_1 [3:0] $end
$var wire 4 | In_2 [3:0] $end
$var wire 4 } In_3 [3:0] $end
$var wire 4 ~ In_4 [3:0] $end
$var wire 3 !" sel [2:0] $end
$var reg 4 "" Out [3:0] $end
$upscope $end
$scope module M1 $end
$var wire 4 #" Mul_In1 [3:0] $end
$var wire 4 $" Mul_In2 [3:0] $end
$var wire 8 %" Mul_Out [7:0] $end
$upscope $end
$scope module M2 $end
$var wire 4 &" Mul_In1 [3:0] $end
$var wire 4 '" Mul_In2 [3:0] $end
$var wire 8 (" Mul_Out [7:0] $end
$upscope $end
$scope module O1 $end
$var wire 11 )" In_0 [10:0] $end
$var wire 11 *" In_1 [10:0] $end
$var wire 11 +" In_2 [10:0] $end
$var wire 11 ," In_3 [10:0] $end
$var wire 11 -" In_4 [10:0] $end
$var wire 3 ." sel [2:0] $end
$var reg 11 /" Out [10:0] $end
$upscope $end
$scope module O2 $end
$var wire 11 0" In_0 [10:0] $end
$var wire 11 1" In_1 [10:0] $end
$var wire 11 2" In_2 [10:0] $end
$var wire 11 3" In_3 [10:0] $end
$var wire 11 4" In_4 [10:0] $end
$var wire 3 5" sel [2:0] $end
$var reg 11 6" Out [10:0] $end
$upscope $end
$upscope $end
$upscope $end
$enddefinitions $end
$comment Show the parameter values. $end
$dumpall
$end
#0
$dumpvars
b1101 6"
b0 5"
bx 4"
bx 3"
bx 2"
bx 1"
b1101 0"
b11000 /"
b0 ."
bx -"
bx ,"
bx +"
b100101 *"
b11000 )"
b1101 ("
b1101 '"
b1 &"
b11000 %"
b110 $"
b100 #"
b1101 ""
b0 !"
b111 ~
b1010 }
b110 |
b1100 {
b1101 z
b1 y
b0 x
b1101 w
b10 v
b1101 u
b11 t
b1 s
b110 r
b0 q
b101 p
b101 o
b1001 n
b1101 m
b110 l
b100 k
b0 j
b1 i
b101 h
b1101 g
b1001 f
b100 e
b11000 d
b1101 c
b100101 b
b0 a
b0 `
b0 _
b0 ^
bx ]
bx \
bx [
bx Z
bx Y
bx X
bx W
b100101 V
b11000 U
b1101 T
b100101 S
b100 R
b110 Q
b1 P
b1101 O
b11000 N
b1101 M
b1101 L
b1 K
b10 J
b101 I
b1101 H
b1101 G
b11 F
b1001 E
b1 D
b100 C
b111 B
b101 A
b1010 @
b101 ?
b110 >
b1001 =
b1100 <
b1101 ;
b1101 :
b110 9
b0 8
b1000001110 7
b1101 6
b1 5
b10 4
b101 3
b1101 2
b1101 1
b11 0
b1001 /
b1 .
b100 -
b111 ,
b101 +
b1010 *
b101 )
b110 (
b1001 '
b1100 &
b1101 %
b1101 $
b110 #
0"
b0 !
$end
#1
b100100 T
b100100 c
b100100 6"
b10011001 S
b10011001 b
b1110101 U
b1110101 d
b1110101 /"
b1001 R
b1001 k
b1001 #"
b1110101 )"
b1110101 N
b1110101 %"
b1101 Q
b1101 r
b1101 $"
b11 P
b11 y
b11 &"
b100100 0"
b100100 M
b100100 ("
b1100 O
b1100 ""
b1100 '"
b10011001 W
b10011001 +"
b1 `
b1 j
b1 q
b1 x
b1 !"
b1 ^
1"
#2
0"
#3
b11000011 S
b11000011 b
b1001110 T
b1001110 c
b1001110 6"
b1101 R
b1101 k
b1101 #"
b1110101 )"
b1110101 N
b1110101 %"
b1001 Q
b1001 r
b1001 $"
b1101 P
b1101 y
b1101 &"
b1001110 0"
b1001110 M
b1001110 ("
b110 O
b110 ""
b110 '"
b11000011 X
b11000011 ,"
b10 `
b10 j
b10 q
b10 x
b10 !"
b10 ^
1"
#4
0"
#5
b10100 T
b10100 c
b10100 6"
b101101 S
b101101 b
b11001 U
b11001 d
b11001 /"
b101 R
b101 k
b101 #"
b11001 )"
b11001 N
b11001 %"
b101 Q
b101 r
b101 $"
b10 P
b10 y
b10 &"
b10100 0"
b10100 M
b10100 ("
b1010 O
b1010 ""
b1010 '"
b101101 Y
b101101 -"
b11 `
b11 j
b11 q
b11 x
b11 !"
b11 ^
1"
#6
0"
#7
b101 U
b101 d
b101 /"
b1100000 S
b1100000 b
b1011011 T
b1011011 c
b1011011 6"
b101 )"
b101 N
b101 %"
b1 R
b1 k
b1 #"
b1101 P
b1101 y
b1101 &"
b1011011 0"
b1011011 M
b1011011 ("
b111 O
b111 ""
b111 '"
b1100000 Z
b1100000 1"
b100 `
b100 j
b100 q
b100 x
b100 !"
b100 ^
1"
#8
0"
#9
b0 R
b0 k
b0 #"
b0 )"
b0 N
b0 %"
b0 Q
b0 r
b0 $"
b0 P
b0 y
b0 &"
b0 0"
b0 M
b0 ("
b0 O
b0 ""
b0 '"
b10000101 [
b10000101 2"
b100101 U
b100101 d
b100101 /"
b10000101 S
b10000101 b
b1100000 T
b1100000 c
b1100000 6"
b1 a
b1 ."
b1 5"
b101 `
b101 j
b101 q
b101 x
b101 !"
b101 ^
1"
#10
0"
#11
b100011110 \
b100011110 3"
b10011001 U
b10011001 d
b10011001 /"
b100011110 S
b100011110 b
b10000101 T
b10000101 c
b10000101 6"
b10 a
b10 ."
b10 5"
b110 `
b110 j
b110 q
b110 x
b110 !"
b110 ^
1"
#12
0"
#13
b111100001 ]
b111100001 4"
b11000011 U
b11000011 d
b11000011 /"
b111100001 S
b111100001 b
b100011110 T
b100011110 c
b100011110 6"
b11 a
b11 ."
b11 5"
b111 `
b111 j
b111 q
b111 x
b111 !"
b111 ^
1"
#14
0"
#15
b11000 )"
b11000 N
b11000 %"
b100 R
b100 k
b100 #"
b110 Q
b110 r
b110 $"
b1101 0"
b1101 M
b1101 ("
b1 P
b1 y
b1 &"
b1101 O
b1101 ""
b1101 '"
b1000001110 !
b1000001110 _
b101101 U
b101101 d
b101101 /"
b1000001110 S
b1000001110 b
b111100001 T
b111100001 c
b111100001 6"
b100 a
b100 ."
b100 5"
b0 `
b0 j
b0 q
b0 x
b0 !"
b1000 ^
1"
#16
0"
#17
b100101 V
b100101 *"
b11000 U
b11000 d
b11000 /"
b100101 S
b100101 b
b1101 T
b1101 c
b1101 6"
b0 a
b0 ."
b0 5"
b0 ^
1"
#18
0"
#19
b100100 T
b100100 c
b100100 6"
b10011001 S
b10011001 b
b1110101 U
b1110101 d
b1110101 /"
b1001 R
b1001 k
b1001 #"
b1110101 )"
b1110101 N
b1110101 %"
b1101 Q
b1101 r
b1101 $"
b11 P
b11 y
b11 &"
b100100 0"
b100100 M
b100100 ("
b1100 O
b1100 ""
b1100 '"
b10011001 W
b10011001 +"
b1 `
b1 j
b1 q
b1 x
b1 !"
b1 ^
1"
#20
b10011100 V
b10011100 *"
b10010110 T
b10010110 c
b10010110 6"
b10011100 S
b10011100 b
b110 U
b110 d
b110 /"
b1010 O
b1010 ""
b1010 '"
b11 Q
b11 r
b11 $"
b10010110 0"
b10010110 M
b10010110 ("
b1111 P
b1111 y
b1111 &"
b110 )"
b110 N
b110 %"
b10 R
b10 k
b10 #"
b0 !
b0 _
b0 `
b0 j
b0 q
b0 x
b0 !"
b0 ^
0"
b1001010100 7
b11 ,
b11 B
b11 ~
b1101 +
b1101 A
b1101 p
b11 *
b11 @
b11 }
b110 )
b110 ?
b110 o
b1101 (
b1101 >
b1101 |
b1010 '
b1010 =
b1010 n
b0 &
b0 <
b0 {
b0 %
b0 ;
b0 m
b1010 $
b1010 :
b1010 z
b11 #
b11 9
b11 l
b101 6
b101 L
b101 w
b1101 5
b1101 K
b1101 i
b1101 4
b1101 J
b1101 v
b1100 3
b1100 I
b1100 h
b101 2
b101 H
b101 u
b1000 1
b1000 G
b1000 g
b1110 0
b1110 F
b1110 t
b10 /
b10 E
b10 f
b1111 .
b1111 D
b1111 s
b10 -
b10 C
b10 e
b1 8
#21
b0 T
b0 c
b0 6"
b0 S
b0 b
b0 U
b0 d
b0 /"
b0 )"
b0 N
b0 %"
b0 Q
b0 r
b0 $"
b1110 P
b1110 y
b1110 &"
b0 0"
b0 M
b0 ("
b0 O
b0 ""
b0 '"
b0 W
b0 +"
b1 `
b1 j
b1 q
b1 x
b1 !"
b1 ^
1"
#22
0"
#23
b1000001 T
b1000001 c
b1000001 6"
b10010001 S
b10010001 b
b1010000 U
b1010000 d
b1010000 /"
b1000 R
b1000 k
b1000 #"
b1010000 )"
b1010000 N
b1010000 %"
b1010 Q
b1010 r
b1010 $"
b101 P
b101 y
b101 &"
b1000001 0"
b1000001 M
b1000001 ("
b1101 O
b1101 ""
b1101 '"
b10010001 X
b10010001 ,"
b10 `
b10 j
b10 q
b10 x
b10 !"
b10 ^
1"
#24
0"
#25
b100111 T
b100111 c
b100111 6"
b1101111 S
b1101111 b
b1001000 U
b1001000 d
b1001000 /"
b1100 R
b1100 k
b1100 #"
b1001000 )"
b1001000 N
b1001000 %"
b110 Q
b110 r
b110 $"
b1101 P
b1101 y
b1101 &"
b100111 0"
b100111 M
b100111 ("
b11 O
b11 ""
b11 '"
b1101111 Y
b1101111 -"
b11 `
b11 j
b11 q
b11 x
b11 !"
b11 ^
1"
#26
0"
#27
b10101001 U
b10101001 d
b10101001 /"
b10111000 S
b10111000 b
b1111 T
b1111 c
b1111 6"
b1101 R
b1101 k
b1101 #"
b10101001 )"
b10101001 N
b10101001 %"
b1101 Q
b1101 r
b1101 $"
b1111 0"
b1111 M
b1111 ("
b101 P
b101 y
b101 &"
b10111000 Z
b10111000 1"
b100 `
b100 j
b100 q
b100 x
b100 !"
b100 ^
1"
#28
0"
#29
b0 R
b0 k
b0 #"
b0 )"
b0 N
b0 %"
b0 Q
b0 r
b0 $"
b0 P
b0 y
b0 &"
b0 0"
b0 M
b0 ("
b0 O
b0 ""
b0 '"
b101010100 [
b101010100 2"
b10011100 U
b10011100 d
b10011100 /"
b101010100 S
b101010100 b
b10111000 T
b10111000 c
b10111000 6"
b1 a
b1 ."
b1 5"
b101 `
b101 j
b101 q
b101 x
b101 !"
b101 ^
1"
#30
0"
#31
b101010100 \
b101010100 3"
b0 U
b0 d
b0 /"
b101010100 S
b101010100 b
b101010100 T
b101010100 c
b101010100 6"
b10 a
b10 ."
b10 5"
b110 `
b110 j
b110 q
b110 x
b110 !"
b110 ^
1"
#32
0"
#33
b111100101 ]
b111100101 4"
b111100101 S
b111100101 b
b10010001 U
b10010001 d
b10010001 /"
b11 a
b11 ."
b11 5"
b111 `
b111 j
b111 q
b111 x
b111 !"
b111 ^
1"
#34
0"
#35
b110 )"
b110 N
b110 %"
b10 R
b10 k
b10 #"
b11 Q
b11 r
b11 $"
b10010110 0"
b10010110 M
b10010110 ("
b1111 P
b1111 y
b1111 &"
b1010 O
b1010 ""
b1010 '"
b1001010100 !
b1001010100 _
b1101111 U
b1101111 d
b1101111 /"
b1001010100 S
b1001010100 b
b111100101 T
b111100101 c
b111100101 6"
b100 a
b100 ."
b100 5"
b0 `
b0 j
b0 q
b0 x
b0 !"
b1000 ^
1"
#36
0"
#37
b10011100 V
b10011100 *"
b110 U
b110 d
b110 /"
b10011100 S
b10011100 b
b10010110 T
b10010110 c
b10010110 6"
b0 a
b0 ."
b0 5"
b0 ^
1"
#38
0"
#39
b0 T
b0 c
b0 6"
b0 S
b0 b
b0 U
b0 d
b0 /"
b0 )"
b0 N
b0 %"
b0 Q
b0 r
b0 $"
b1110 P
b1110 y
b1110 &"
b0 0"
b0 M
b0 ("
b0 O
b0 ""
b0 '"
b0 W
b0 +"
b1 `
b1 j
b1 q
b1 x
b1 !"
b1 ^
1"
#40
b1011 R
b1011 k
b1011 #"
b101 P
b101 y
b101 &"
b1001000 V
b1001000 *"
b110010 T
b110010 c
b110010 6"
b1001000 S
b1001000 b
b10110 U
b10110 d
b10110 /"
b110010 0"
b110010 M
b110010 ("
b1010 O
b1010 ""
b1010 '"
b10110 )"
b10110 N
b10110 %"
b10 Q
b10 r
b10 $"
b0 !
b0 _
b0 `
b0 j
b0 q
b0 x
b0 !"
b0 ^
0"
b1011101010 7
b1110 ,
b1110 B
b1110 ~
b110 +
b110 A
b110 p
b110 *
b110 @
b110 }
b1011 )
b1011 ?
b1011 o
b1001 (
b1001 >
b1001 |
b1000 '
b1000 =
b1000 n
b1000 &
b1000 <
b1000 {
b1 %
b1 ;
b1 m
b10 #
b10 9
b10 l
b1100 6
b1100 L
b1100 w
b1010 5
b1010 K
b1010 i
b1010 4
b1010 J
b1010 v
b11 3
b11 I
b11 h
b1111 2
b1111 H
b1111 u
b1101 1
b1101 G
b1101 g
b101 .
b101 D
b101 s
b1011 -
b1011 C
b1011 e
b10 8
#41
b1110000 T
b1110000 c
b1110000 6"
b1110010 S
b1110010 b
b10 U
b10 d
b10 /"
b10 R
b10 k
b10 #"
b10 )"
b10 N
b10 %"
b1 Q
b1 r
b1 $"
b1110 P
b1110 y
b1110 &"
b1110000 0"
b1110000 M
b1110000 ("
b1000 O
b1000 ""
b1000 '"
b1110010 W
b1110010 +"
b1 `
b1 j
b1 q
b1 x
b1 !"
b1 ^
1"
#42
0"
#43
b10000111 T
b10000111 c
b10000111 6"
b11101111 S
b11101111 b
b1101000 U
b1101000 d
b1101000 /"
b1101 R
b1101 k
b1101 #"
b1101000 )"
b1101000 N
b1101000 %"
b1000 Q
b1000 r
b1000 $"
b1111 P
b1111 y
b1111 &"
b10000111 0"
b10000111 M
b10000111 ("
b1001 O
b1001 ""
b1001 '"
b11101111 X
b11101111 ,"
b10 `
b10 j
b10 q
b10 x
b10 !"
b10 ^
1"
#44
0"
#45
b111100 T
b111100 c
b111100 6"
b1011101 S
b1011101 b
b100001 U
b100001 d
b100001 /"
b11 R
b11 k
b11 #"
b100001 )"
b100001 N
b100001 %"
b1011 Q
b1011 r
b1011 $"
b1010 P
b1010 y
b1010 &"
b111100 0"
b111100 M
b111100 ("
b110 O
b110 ""
b110 '"
b1011101 Y
b1011101 -"
b11 `
b11 j
b11 q
b11 x
b11 !"
b11 ^
1"
#46
0"
#47
b111100 U
b111100 d
b111100 /"
b11100100 S
b11100100 b
b10101000 T
b10101000 c
b10101000 6"
b1010 R
b1010 k
b1010 #"
b111100 )"
b111100 N
b111100 %"
b110 Q
b110 r
b110 $"
b1100 P
b1100 y
b1100 &"
b10101000 0"
b10101000 M
b10101000 ("
b1110 O
b1110 ""
b1110 '"
b11100100 Z
b11100100 1"
b100 `
b100 j
b100 q
b100 x
b100 !"
b100 ^
1"
#48
0"
#49
b0 R
b0 k
b0 #"
b0 )"
b0 N
b0 %"
b0 Q
b0 r
b0 $"
b0 P
b0 y
b0 &"
b0 0"
b0 M
b0 ("
b0 O
b0 ""
b0 '"
b100101100 [
b100101100 2"
b1001000 U
b1001000 d
b1001000 /"
b100101100 S
b100101100 b
b11100100 T
b11100100 c
b11100100 6"
b1 a
b1 ."
b1 5"
b101 `
b101 j
b101 q
b101 x
b101 !"
b101 ^
1"
#50
0"
#51
b110011110 \
b110011110 3"
b1110010 U
b1110010 d
b1110010 /"
b110011110 S
b110011110 b
b100101100 T
b100101100 c
b100101100 6"
b10 a
b10 ."
b10 5"
b110 `
b110 j
b110 q
b110 x
b110 !"
b110 ^
1"
#52
0"
#53
b1010001101 ]
b1010001101 4"
b11101111 U
b11101111 d
b11101111 /"
b1010001101 S
b1010001101 b
b110011110 T
b110011110 c
b110011110 6"
b11 a
b11 ."
b11 5"
b111 `
b111 j
b111 q
b111 x
b111 !"
b111 ^
1"
#54
0"
#55
b10110 )"
b10110 N
b10110 %"
b1011 R
b1011 k
b1011 #"
b10 Q
b10 r
b10 $"
b110010 0"
b110010 M
b110010 ("
b101 P
b101 y
b101 &"
b1010 O
b1010 ""
b1010 '"
b1011101010 !
b1011101010 _
b1011101 U
b1011101 d
b1011101 /"
b1011101010 S
b1011101010 b
b1010001101 T
b1010001101 c
b1010001101 6"
b100 a
b100 ."
b100 5"
b0 `
b0 j
b0 q
b0 x
b0 !"
b1000 ^
1"
#56
0"
#57
b1001000 V
b1001000 *"
b10110 U
b10110 d
b10110 /"
b1001000 S
b1001000 b
b110010 T
b110010 c
b110010 6"
b0 a
b0 ."
b0 5"
b0 ^
1"
#58
0"
#59
b1110000 T
b1110000 c
b1110000 6"
b1110010 S
b1110010 b
b10 U
b10 d
b10 /"
b10 R
b10 k
b10 #"
b10 )"
b10 N
b10 %"
b1 Q
b1 r
b1 $"
b1110 P
b1110 y
b1110 &"
b1110000 0"
b1110000 M
b1110000 ("
b1000 O
b1000 ""
b1000 '"
b1110010 W
b1110010 +"
b1 `
b1 j
b1 q
b1 x
b1 !"
b1 ^
1"
#60
b1100110 V
b1100110 *"
b1011010 T
b1011010 c
b1011010 6"
b1100110 S
b1100110 b
b1100 U
b1100 d
b1100 /"
b1001 O
b1001 ""
b1001 '"
b1 Q
b1 r
b1 $"
b1011010 0"
b1011010 M
b1011010 ("
b1010 P
b1010 y
b1010 &"
b1100 )"
b1100 N
b1100 %"
b1100 R
b1100 k
b1100 #"
b0 !
b0 _
b0 `
b0 j
b0 q
b0 x
b0 !"
b0 ^
0"
b1101100000 7
b1100 ,
b1100 B
b1100 ~
b1111 +
b1111 A
b1111 p
b111 *
b111 @
b111 }
b1000 )
b1000 ?
b1000 o
b1111 (
b1111 >
b1111 |
b1111 '
b1111 =
b1111 n
b1100 &
b1100 <
b1100 {
b10 %
b10 ;
b10 m
b1001 $
b1001 :
b1001 z
b1 #
b1 9
b1 l
b101 6
b101 L
b101 w
b1110 5
b1110 K
b1110 i
b1011 3
b1011 I
b1011 h
b101 1
b101 G
b101 g
b1 0
b1 F
b1 t
b1011 /
b1011 E
b1011 f
b1010 .
b1010 D
b1010 s
b1100 -
b1100 C
b1100 e
b11 8
#61
b1100 T
b1100 c
b1100 6"
b100010 S
b100010 b
b10110 U
b10110 d
b10110 /"
b1011 R
b1011 k
b1011 #"
b10110 )"
b10110 N
b10110 %"
b10 Q
b10 r
b10 $"
b1 P
b1 y
b1 &"
b1100 0"
b1100 M
b1100 ("
b1100 O
b1100 ""
b1100 '"
b100010 W
b100010 +"
b1 `
b1 j
b1 q
b1 x
b1 !"
b1 ^
1"
#62
0"
#63
b11100001 T
b11100001 c
b11100001 6"
b100101100 S
b100101100 b
b1001011 U
b1001011 d
b1001011 /"
b101 R
b101 k
b101 #"
b1001011 )"
b1001011 N
b1001011 %"
b1111 Q
b1111 r
b1111 $"
b1111 P
b1111 y
b1111 &"
b11100001 0"
b11100001 M
b11100001 ("
b1111 O
b1111 ""
b1111 '"
b100101100 X
b100101100 ,"
b10 `
b10 j
b10 q
b10 x
b10 !"
b10 ^
1"
#64
0"
#65
b1000110 T
b1000110 c
b1000110 6"
b10011110 S
b10011110 b
b1011000 U
b1011000 d
b1011000 /"
b1011 R
b1011 k
b1011 #"
b1011000 )"
b1011000 N
b1011000 %"
b1000 Q
b1000 r
b1000 $"
b1010 P
b1010 y
b1010 &"
b1000110 0"
b1000110 M
b1000110 ("
b111 O
b111 ""
b111 '"
b10011110 Y
b10011110 -"
b11 `
b11 j
b11 q
b11 x
b11 !"
b11 ^
1"
#66
0"
#67
b11010010 U
b11010010 d
b11010010 /"
b100001110 S
b100001110 b
b111100 T
b111100 c
b111100 6"
b1110 R
b1110 k
b1110 #"
b11010010 )"
b11010010 N
b11010010 %"
b1111 Q
b1111 r
b1111 $"
b101 P
b101 y
b101 &"
b111100 0"
b111100 M
b111100 ("
b1100 O
b1100 ""
b1100 '"
b100001110 Z
b100001110 1"
b100 `
b100 j
b100 q
b100 x
b100 !"
b100 ^
1"
#68
0"
#69
b0 R
b0 k
b0 #"
b0 )"
b0 N
b0 %"
b0 Q
b0 r
b0 $"
b0 P
b0 y
b0 &"
b0 0"
b0 M
b0 ("
b0 O
b0 ""
b0 '"
b101110100 [
b101110100 2"
b1100110 U
b1100110 d
b1100110 /"
b101110100 S
b101110100 b
b100001110 T
b100001110 c
b100001110 6"
b1 a
b1 ."
b1 5"
b101 `
b101 j
b101 q
b101 x
b101 !"
b101 ^
1"
#70
0"
#71
b110010110 \
b110010110 3"
b100010 U
b100010 d
b100010 /"
b110010110 S
b110010110 b
b101110100 T
b101110100 c
b101110100 6"
b10 a
b10 ."
b10 5"
b110 `
b110 j
b110 q
b110 x
b110 !"
b110 ^
1"
#72
0"
