memory.v
module memory_h0(out,in,clk); 
  input [3:0] in; 
  input clk; 
  output reg [7:0] out; 
  integer j; 
  parameter h0 = 1; 
  reg [7:0] memory[0:((2**4)-1)]; 
  initial begin 
    for (j = 0; j < ((2 ** 4)); j++) begin 
      memory[j] = h0 * j; 
    end 
  end 
  always @(posedge clk) begin 
    out <= memory[in]; 
  end
endmodule
module memory_h1(out,in,clk); 
  input [3:0] in; 
  input clk; 
  output reg [7:0] out; 
  integer j; 
  parameter h1 = 2; 
  reg [7:0] memory[0:((2**4)-1)]; 
  initial begin 
    for (j = 0; j < ((2 ** 4)); j++) begin 
      memory[j] = h1 * j; 
    end 
  end 
  always @(posedge clk) begin 
    out <= memory[in]; 
  end
endmodule
module memory_h2(out,in,clk); 
input [3:0] in; 
  input clk; 
  output reg [7:0] out; 
  integer j; 
  parameter h2 = 3; 
  reg [7:0] memory[0:((2**4)-1)]; 
  initial begin 
    for (j = 0; j < ((2 ** 4)); j++) begin 
      memory[j] = h2 * j; 
    end 
  end 
  always @(posedge clk) begin 
    out <= memory[in]; 
  end
endmodule
module memory_h3(out,in,clk); 
  input [3:0] in; 
  input clk; 
  output reg [7:0] out; 
  integer j; 
  parameter h3 = 4; 
  reg [7:0] memory[0:((2**4)-1)]; 
  initial begin 
    for (j = 0; j < ((2 ** 4)); j++) begin 
      memory[j] = h3 * j; 
    end 
  end 
  always @(posedge clk) begin 
    out <= memory[in]; 
  end
endmodule
module memory_h4(out,in,clk); 
  input [3:0] in; 
  input clk; 
  output reg [7:0] out; 
  integer j; 
  parameter h4 = 5; 
  reg [7:0] memory[0:((2**4)-1)]; 
  initial begin 
    for (j = 0; j < ((2 ** 4)); j++) begin 
      memory[j] = h4 * j; 
    end 
  end 
  always @(posedge clk) begin 
    out <= memory[in]; 
  end
endmodule
module memory_h5(out,in,clk); 
  input [3:0] in; 
  input clk; 
  output reg [7:0] out; 
  integer j; 
  parameter h5 = 6; 
  reg [7:0] memory[0:((2**4)-1)]; 
initial begin 
    for (j = 0; j < ((2 ** 4)); j++) begin 
      memory[j] = h5 * j; 
    end 
  end 
  always @(posedge clk) begin 
    out <= memory[in]; 
  end
endmodule
module memory_h6(out,in,clk); 
  input [3:0] in; 
  input clk; 
  output reg [7:0] out; 
  integer j; 
  parameter h6 = 7; 
  reg [7:0] memory[0:((2**4)-1)]; 
  initial begin 
    for (j = 0; j < ((2 ** 4)); j++) begin 
      memory[j] = h6 * j; 
    end 
  end 
  always @(posedge clk) begin 
    out <= memory[in]; 
  end
endmodule
module memory_h7(out,in,clk); 
  input [3:0] in; 
  input clk; 
  output reg [7:0] out; 
  integer j; 
  parameter h7 = 8; 
  reg [7:0] memory[0:((2**4)-1)]; 
  initial begin 
    for (j = 0; j < ((2 ** 4)); j++) begin 
      memory[j] = h7 * j; 
    end 
  end 
  always @(posedge clk) begin 
    out <= memory[in]; 
  end
endmodule
module memory_h8(out,in,clk); 
  input [3:0] in; 
  input clk; 
  output reg [7:0] out; 
  integer j; 
  parameter h8 = 9; 
  reg [7:0] memory[0:((2**4)-1)]; 
  initial begin 
    for (j = 0; j < ((2 ** 4)); j++) begin 
      memory[j] = h8 * j; 
    end 
  end 
  always @(posedge clk) begin 

    out <= memory[in]; 
  end
endmodule
module memory_h9(out,in,clk); 
  input [3:0] in; 
  input clk; 
  output reg [7:0] out; 
  integer j; 
  parameter h9 = 10; 
  reg [7:0] memory[0:((2**4)-1)]; 
  initial begin 
    for (j = 0; j < ((2 ** 4)); j++) begin 
      memory[j] = h9 * j; 
    end 
  end 
  always @(posedge clk) begin 
    out <= memory[in]; 
  end
endmodule 
 
module adder(out,m0,m1,m2,m3,m4,m5,m6,m7,m8,m9); 
  input [7:0] m0, m1, m2, m3, m4, m5, m6, m7, m8, m9; 
  output [10:0] out; 
  assign out = m0 + m1 + m2 + m3 + m4 + m5 + m6 + m7 + m8 + m9; 
endmodule

Q4.v
`include"memory.v"
module Q4(out,clk,x_0,x_1,x_2,x_3,x_4,x_5,x_6,x_7,x_8,x_9); 
output [10:0]out; 
input [3:0] x_0,x_1,x_2,x_3,x_4,x_5,x_6,x_7,x_8,x_9; 
wire [7:0] m_0,m_1,m_2,m_3,m_4,m_5,m_6,m_7,m_8,m_9; 
input clk; 
 
memory_h0 hh0(m_0,x_0,clk); 
memory_h1 hh1(m_1,x_1,clk); 
memory_h2 hh2(m_2,x_2,clk); 
memory_h3 hh3(m_3,x_3,clk); 
memory_h4 hh4(m_4,x_4,clk); 
memory_h5 hh5(m_5,x_5,clk); 
memory_h6 hh6(m_6,x_6,clk); 
memory_h7 hh7(m_7,x_7,clk); 
memory_h8 hh8(m_8,x_8,clk); 
memory_h9 hh9(m_9,x_9,clk); 
 
adder add(out,m_0,m_1,m_2,m_3,m_4,m_5,m_6,m_7,m_8,m_9); 
endmodule

Q4_tb.v
`timescale 1ns / 1ns
`include "Q4.v"
module Q4_tb; 
  reg [3:0] x_0, x_1, x_2, x_3, x_4, x_5, x_6, x_7, x_8, x_9; 
  reg clk; 
  wire [10:0] Output; 
  Q4 uut (Output,clk,x_0,x_1,x_2,x_3,x_4,x_5,x_6,x_7,x_8,x_9); 
  integer i, j, expected; 
  initial begin 
    $monitor($time, "x0=%d x1=%d x2=%d x3=%d x4=%d x5=%d x6=%d x7=%d x8=%d x9=%d Output=%d expected=%d", x_0, x_1, x_2, x_3, x_4, x_5, x_6, x_7, x_8, x_9, Output, expected); 
  end 
  initial begin 
    clk = 1'b0; 
    forever #5 clk = ~clk; 
  end 
  initial begin 
    for (i = 0; i < 19; i++) begin 
      #10 x_0 = $random; 
      x_1 = $random; 
      x_2 = $random; 
      x_3 = $random; 
      x_4 = $random; 
      x_5 = $random; 
      x_6 = $random; 
      x_7 = $random; 
      x_8 = $random; 
      x_9 = $random; 
      expected=x_0*(1)+x_1*(2)+x_2*(3)+x_3*(4)+x_4*(5)+x_5*(6)+x_6*(7)+x_7*(8)+x_8*(9)+x_9*(10); 
    end 
  end 
  initial begin 
    $dumpfile("Q4.vcd"); 
    $dumpvars; 
  end 
  initial begin 
    #200 $finish; 
  end
endmodule

Q4.vcd
$date
	Sun Feb 04 22:12:40 2024
$end
$version
	Icarus Verilog
$end
$timescale
	1ns
$end
$scope module Q4_tb $end
$var wire 11 ! Output [10:0] $end
$var reg 1 " clk $end
$var reg 4 # x_0 [3:0] $end
$var reg 4 $ x_1 [3:0] $end
$var reg 4 % x_2 [3:0] $end
$var reg 4 & x_3 [3:0] $end
$var reg 4 ' x_4 [3:0] $end
$var reg 4 ( x_5 [3:0] $end
$var reg 4 ) x_6 [3:0] $end
$var reg 4 * x_7 [3:0] $end
$var reg 4 + x_8 [3:0] $end
$var reg 4 , x_9 [3:0] $end
$var integer 32 - expected [31:0] $end
$var integer 32 . i [31:0] $end
$scope module uut $end
$var wire 1 " clk $end
$var wire 4 / x_0 [3:0] $end
$var wire 4 0 x_1 [3:0] $end
$var wire 4 1 x_2 [3:0] $end
$var wire 4 2 x_3 [3:0] $end
$var wire 4 3 x_4 [3:0] $end
$var wire 4 4 x_5 [3:0] $end
$var wire 4 5 x_6 [3:0] $end
$var wire 4 6 x_7 [3:0] $end
$var wire 4 7 x_8 [3:0] $end
$var wire 4 8 x_9 [3:0] $end
$var wire 11 9 out [10:0] $end
$var wire 8 : m_9 [7:0] $end
$var wire 8 ; m_8 [7:0] $end
$var wire 8 < m_7 [7:0] $end
$var wire 8 = m_6 [7:0] $end
$var wire 8 > m_5 [7:0] $end
$var wire 8 ? m_4 [7:0] $end
$var wire 8 @ m_3 [7:0] $end
$var wire 8 A m_2 [7:0] $end
$var wire 8 B m_1 [7:0] $end
$var wire 8 C m_0 [7:0] $end
$scope module add $end
$var wire 11 D out [10:0] $end
$var wire 8 E m9 [7:0] $end
$var wire 8 F m8 [7:0] $end
$var wire 8 G m7 [7:0] $end
$var wire 8 H m6 [7:0] $end
$var wire 8 I m5 [7:0] $end
$var wire 8 J m4 [7:0] $end
$var wire 8 K m3 [7:0] $end
$var wire 8 L m2 [7:0] $end
$var wire 8 M m1 [7:0] $end
$var wire 8 N m0 [7:0] $end
$upscope $end
$scope module hh0 $end
$var wire 1 " clk $end
$var wire 4 O in [3:0] $end
$var parameter 32 P h0 $end
$var reg 8 Q out [7:0] $end
$var integer 32 R j [31:0] $end
$upscope $end
$scope module hh1 $end
$var wire 1 " clk $end
$var wire 4 S in [3:0] $end
$var parameter 32 T h1 $end
$var reg 8 U out [7:0] $end
$var integer 32 V j [31:0] $end
$upscope $end
$scope module hh2 $end
$var wire 1 " clk $end
$var wire 4 W in [3:0] $end
$var parameter 32 X h2 $end
$var reg 8 Y out [7:0] $end
$var integer 32 Z j [31:0] $end
$upscope $end
$scope module hh3 $end
$var wire 1 " clk $end
$var wire 4 [ in [3:0] $end
$var parameter 32 \ h3 $end
$var reg 8 ] out [7:0] $end
$var integer 32 ^ j [31:0] $end
$upscope $end
$scope module hh4 $end
$var wire 1 " clk $end
$var wire 4 _ in [3:0] $end
$var parameter 32 ` h4 $end
$var reg 8 a out [7:0] $end
$var integer 32 b j [31:0] $end
$upscope $end
$scope module hh5 $end
$var wire 1 " clk $end
$var wire 4 c in [3:0] $end
$var parameter 32 d h5 $end
$var reg 8 e out [7:0] $end
$var integer 32 f j [31:0] $end
$upscope $end
$scope module hh6 $end
$var wire 1 " clk $end
$var wire 4 g in [3:0] $end
$var parameter 32 h h6 $end
$var reg 8 i out [7:0] $end
$var integer 32 j j [31:0] $end
$upscope $end
$scope module hh7 $end
$var wire 1 " clk $end
$var wire 4 k in [3:0] $end
$var parameter 32 l h7 $end
$var reg 8 m out [7:0] $end
$var integer 32 n j [31:0] $end
$upscope $end
$scope module hh8 $end
$var wire 1 " clk $end
$var wire 4 o in [3:0] $end
$var parameter 32 p h8 $end
$var reg 8 q out [7:0] $end
$var integer 32 r j [31:0] $end
$upscope $end
$scope module hh9 $end
$var wire 1 " clk $end
$var wire 4 s in [3:0] $end
$var parameter 32 t h9 $end
$var reg 8 u out [7:0] $end
$var integer 32 v j [31:0] $end
$upscope $end
$upscope $end
$upscope $end
$enddefinitions $end
$comment Show the parameter values. $end
$dumpall
b1010 t
b1001 p
b1000 l
b111 h
b110 d
b101 `
b100 \
b11 X
b10 T
b1 P
$end
#0
$dumpvars
b10000 v
bx u
bx s
b10000 r
bx q
bx o
b10000 n
bx m
bx k
b10000 j
bx i
bx g
b10000 f
bx e
bx c
b10000 b
bx a
bx _
b10000 ^
bx ]
bx [
b10000 Z
bx Y
bx W
b10000 V
bx U
bx S
b10000 R
bx Q
bx O
bx N
bx M
bx L
bx K
bx J
bx I
bx H
bx G
bx F
bx E
bx D
bx C
bx B
bx A
bx @
bx ?
bx >
bx =
bx <
bx ;
bx :
bx 9
bx 8
bx 7
bx 6
bx 5
bx 4
bx 3
bx 2
bx 1
bx 0
bx /
b0 .
bx -
bx ,
bx +
bx *
bx )
bx (
bx '
bx &
bx %
bx $
bx #
0"
bx !
$end
#5
1"
#10
0"
b1 .
b101111010 -
b1101 ,
b1101 8
b1101 s
b1 +
b1 7
b1 o
b10 *
b10 6
b10 k
b101 )
b101 5
b101 g
b1101 (
b1101 4
b1101 c
b1101 '
b1101 3
b1101 _
b11 &
b11 2
b11 [
b1001 %
b1001 1
b1001 W
b1 $
b1 0
b1 S
b100 #
b100 /
b100 O
#15
b101111010 !
b101111010 9
b101111010 D
b10000010 :
b10000010 E
b10000010 u
b1001 ;
b1001 F
b1001 q
b10000 <
b10000 G
b10000 m
b100011 =
b100011 H
b100011 i
b1001110 >
b1001110 I
b1001110 e
b1000001 ?
b1000001 J
b1000001 a
b1100 @
b1100 K
b1100 ]
b11011 A
b11011 L
b11011 Y
b10 B
b10 M
b10 U
b100 C
b100 N
b100 Q
1"
#20
0"
b10 .
b110101110 -
b111 ,
b111 8
b111 s
b101 +
b101 7
b101 o
b1010 *
b1010 6
b1010 k
b110 (
b110 4
b110 c
b1001 '
b1001 3
b1001 _
b1100 &
b1100 2
b1100 [
b1101 %
b1101 1
b1101 W
b1101 $
b1101 0
b1101 S
b110 #
b110 /
b110 O
#25
b110 C
b110 N
b110 Q
b11010 B
b11010 M
b11010 U
b100111 A
b100111 L
b100111 Y
b110000 @
b110000 K
b110000 ]
b101101 ?
b101101 J
b101101 a
b100100 >
b100100 I
b100100 e
b1010000 <
b1010000 G
b1010000 m
b101101 ;
b101101 F
b101101 q
b110101110 !
b110101110 9
b110101110 D
b1000110 :
b1000110 E
b1000110 u
1"
#30
0"
b11 .
b1000000111 -
b101 ,
b101 8
b101 s
b1101 +
b1101 7
b1101 o
b1101 *
b1101 6
b1101 k
b1100 )
b1100 5
b1100 g
b101 (
b101 4
b101 c
b1000 '
b1000 3
b1000 _
b1110 &
b1110 2
b1110 [
b10 %
b10 1
b10 W
b1111 $
b1111 0
b1111 S
b10 #
b10 /
b10 O
#35
b110010 :
b110010 E
b110010 u
b1110101 ;
b1110101 F
b1110101 q
b1101000 <
b1101000 G
b1101000 m
b1010100 =
b1010100 H
b1010100 i
b11110 >
b11110 I
b11110 e
b101000 ?
b101000 J
b101000 a
b111000 @
b111000 K
b111000 ]
b110 A
b110 L
b110 Y
b11110 B
b11110 M
b11110 U
b1000000111 !
b1000000111 9
b1000000111 D
b10 C
b10 N
b10 Q
1"
#40
0"
b100 .
b101101100 -
b11 ,
b11 8
b11 s
b11 *
b11 6
b11 k
b110 )
b110 5
b110 g
b1101 (
b1101 4
b1101 c
b1010 '
b1010 3
b1010 _
b0 &
b0 2
b0 [
b0 %
b0 1
b0 W
b1010 $
b1010 0
b1010 S
b11 #
b11 /
b11 O
#45
b11 C
b11 N
b11 Q
b10100 B
b10100 M
b10100 U
b0 A
b0 L
b0 Y
b0 @
b0 K
b0 ]
b110010 ?
b110010 J
b110010 a
b1001110 >
b1001110 I
b1001110 e
b101010 =
b101010 H
b101010 i
b11000 <
b11000 G
b11000 m
b101101100 !
b101101100 9
b101101100 D
b11110 :
b11110 E
b11110 u
1"
#50
0"
b101 .
b1000100101 -
b1100 ,
b1100 8
b1100 s
b1010 +
b1010 7
b1010 o
b1010 *
b1010 6
b1010 k
b11 )
b11 5
b11 g
b1111 (
b1111 4
b1111 c
b1101 '
b1101 3
b1101 _
b1110 &
b1110 2
b1110 [
b10 %
b10 1
b10 W
b101 $
b101 0
b101 S
b1011 #
b1011 /
b1011 O
#55
b1111000 :
b1111000 E
b1111000 u
b1011010 ;
b1011010 F
b1011010 q
b1010000 <
b1010000 G
b1010000 m
b10101 =
b10101 H
b10101 i
b1011010 >
b1011010 I
b1011010 e
b1000001 ?
b1000001 J
b1000001 a
b111000 @
b111000 K
b111000 ]
b110 A
b110 L
b110 Y
b1010 B
b1010 M
b1010 U
b1000100101 !
b1000100101 9
b1000100101 D
b1011 C
b1011 N
b1011 Q
1"
#60
0"
b110 .
b111010110 -
b1110 ,
b1110 8
b1110 s
b110 +
b110 7
b110 o
b110 *
b110 6
b110 k
b1011 )
b1011 5
b1011 g
b1001 (
b1001 4
b1001 c
b1000 '
b1000 3
b1000 _
b1000 &
b1000 2
b1000 [
b1 %
b1 1
b1 W
b1010 $
b1010 0
b1010 S
b10 #
b10 /
b10 O
#65
b10 C
b10 N
b10 Q
b10100 B
b10100 M
b10100 U
b11 A
b11 L
b11 Y
b100000 @
b100000 K
b100000 ]
b101000 ?
b101000 J
b101000 a
b110110 >
b110110 I
b110110 e
b1001101 =
b1001101 H
b1001101 i
b110000 <
b110000 G
b110000 m
b110110 ;
b110110 F
b110110 q
b111010110 !
b111010110 9
b111010110 D
b10001100 :
b10001100 E
b10001100 u
1"
#70
0"
b111 .
b1000000101 -
b101 ,
b101 8
b101 s
b1110 +
b1110 7
b1110 o
b1010 *
b1010 6
b1010 k
b1111 (
b1111 4
b1111 c
b101 '
b101 3
b101 _
b1 &
b1 2
b1 [
b1011 %
b1011 1
b1011 W
b1100 #
b1100 /
b1100 O
#75
b110010 :
b110010 E
b110010 u
b1111110 ;
b1111110 F
b1111110 q
b1010000 <
b1010000 G
b1010000 m
b1011010 >
b1011010 I
b1011010 e
b11001 ?
b11001 J
b11001 a
b100 @
b100 K
b100 ]
b100001 A
b100001 L
b100001 Y
b1000000101 !
b1000000101 9
b1000000101 D
b1100 C
b1100 N
b1100 Q
1"
#80
0"
b1000 .
b1001011101 -
b1100 ,
b1100 8
b1100 s
b1111 +
b1111 7
b1111 o
b111 *
b111 6
b111 k
b1000 )
b1000 5
b1000 g
b1111 '
b1111 3
b1111 _
b1100 &
b1100 2
b1100 [
b10 %
b10 1
b10 W
b1001 $
b1001 0
b1001 S
b1 #
b1 /
b1 O
#85
b1 C
b1 N
b1 Q
b10010 B
b10010 M
b10010 U
b110 A
b110 L
b110 Y
b110000 @
b110000 K
b110000 ]
b1001011 ?
b1001011 J
b1001011 a
b111000 =
b111000 H
b111000 i
b111000 <
b111000 G
b111000 m
b10000111 ;
b10000111 F
b10000111 q
b1001011101 !
b1001011101 9
b1001011101 D
b1111000 :
b1111000 E
b1111000 u
1"
#90
0"
b1001 .
b101001101 -
b1000 ,
b1000 8
b1000 s
b10 +
b10 7
b10 o
b1100 *
b1100 6
b1100 k
b110 )
b110 5
b110 g
b1 (
b1 4
b1 c
b111 '
b111 3
b111 _
b0 &
b0 2
b0 [
b1001 %
b1001 1
b1001 W
b1011 #
b1011 /
b1011 O
#95
b1010000 :
b1010000 E
b1010000 u
b10010 ;
b10010 F
b10010 q
b1100000 <
b1100000 G
b1100000 m
b101010 =
b101010 H
b101010 i
b110 >
b110 I
b110 e
b100011 ?
b100011 J
b100011 a
b0 @
b0 K
b0 ]
b11011 A
b11011 L
b11011 Y
b101001101 !
b101001101 9
b101001101 D
b1011 C
b1011 N
b1011 Q
1"
#100
0"
b1010 .
b111010100 -
b101 +
b101 7
b101 o
b11 *
b11 6
b11 k
b1111 )
b1111 5
b1111 g
b1001 (
b1001 4
b1001 c
b1101 '
b1101 3
b1101 _
b1110 &
b1110 2
b1110 [
b10 %
b10 1
b10 W
b1101 $
b1101 0
b1101 S
b111 #
b111 /
b111 O
#105
b111 C
b111 N
b111 Q
b11010 B
b11010 M
b11010 U
b110 A
b110 L
b110 Y
b111000 @
b111000 K
b111000 ]
b1000001 ?
b1000001 J
b1000001 a
b110110 >
b110110 I
b110110 e
b1101001 =
b1101001 H
b1101001 i
b11000 <
b11000 G
b11000 m
b111010100 !
b111010100 9
b111010100 D
b101101 ;
b101101 F
b101101 q
1"
#110
0"
b1011 .
b1000010110 -
b110 ,
b110 8
b110 s
b1010 +
b1010 7
b1010 o
b1100 *
b1100 6
b1100 k
b1110 )
b1110 5
b1110 g
b110 (
b110 4
b110 c
b1000 '
b1000 3
b1000 _
b1010 &
b1010 2
b1010 [
b1111 %
b1111 1
b1111 W
b1001 $
b1001 0
b1001 S
b1011 #
b1011 /
b1011 O
#115
b111100 :
b111100 E
b111100 u
b1011010 ;
b1011010 F
b1011010 q
b1100000 <
b1100000 G
b1100000 m
b1100010 =
b1100010 H
b1100010 i
b100100 >
b100100 I
b100100 e
b101000 ?
b101000 J
b101000 a
b101000 @
b101000 K
b101000 ]
b101101 A
b101101 L
b101101 Y
b10010 B
b10010 M
b10010 U
b1000010110 !
b1000010110 9
b1000010110 D
b1011 C
b1011 N
b1011 Q
1"
#120
0"
b1100 .
b111001000 -
b1010 ,
b1010 8
b1010 s
b110 +
b110 7
b110 o
b1011 *
b1011 6
b1011 k
b111 )
b111 5
b111 g
b100 (
b100 4
b100 c
b1111 '
b1111 3
b1111 _
b11 &
b11 2
b11 [
b11 $
b11 0
b11 S
b11 #
b11 /
b11 O
#125
b11 C
b11 N
b11 Q
b110 B
b110 M
b110 U
b1100 @
b1100 K
b1100 ]
b1001011 ?
b1001011 J
b1001011 a
b11000 >
b11000 I
b11000 e
b110001 =
b110001 H
b110001 i
b1011000 <
b1011000 G
b1011000 m
b110110 ;
b110110 F
b110110 q
b111001000 !
b111001000 9
b111001000 D
b1100100 :
b1100100 E
b1100100 u
1"
#130
0"
b1101 .
b110001011 -
b0 +
b0 7
b0 o
b100 *
b100 6
b100 k
b1001 )
b1001 5
b1001 g
b1111 (
b1111 4
b1111 c
b101 '
b101 3
b101 _
b101 &
b101 2
b101 [
b1010 %
b1010 1
b1010 W
b1101 $
b1101 0
b1101 S
b1001 #
b1001 /
b1001 O
#135
b0 ;
b0 F
b0 q
b100000 <
b100000 G
b100000 m
b111111 =
b111111 H
b111111 i
b1011010 >
b1011010 I
b1011010 e
b11001 ?
b11001 J
b11001 a
b10100 @
b10100 K
b10100 ]
b11110 A
b11110 L
b11110 Y
b11010 B
b11010 M
b11010 U
b110001011 !
b110001011 9
b110001011 D
b1001 C
b1001 N
b1001 Q
1"
#140
0"
b1110 .
b1000000011 -
b111 +
b111 7
b111 o
b1110 *
b1110 6
b1110 k
b110 )
b110 5
b110 g
b11 (
b11 4
b11 c
b1101 '
b1101 3
b1101 _
b1010 &
b1010 2
b1010 [
b1100 %
b1100 1
b1100 W
b1110 $
b1110 0
b1110 S
b1011 #
b1011 /
b1011 O
#145
b1011 C
b1011 N
b1011 Q
b11100 B
b11100 M
b11100 U
b100100 A
b100100 L
b100100 Y
b101000 @
b101000 K
b101000 ]
b1000001 ?
b1000001 J
b1000001 a
b10010 >
b10010 I
b10010 e
b101010 =
b101010 H
b101010 i
b1110000 <
b1110000 G
b1110000 m
b1000000011 !
b1000000011 9
b1000000011 D
b111111 ;
b111111 F
b111111 q
1"
#150
0"
b1111 .
b111000000 -
b1101 ,
b1101 8
b1101 s
b1011 +
b1011 7
b1011 o
b1001 *
b1001 6
b1001 k
b100 )
b100 5
b100 g
b100 '
b100 3
b100 _
b1000 &
b1000 2
b1000 [
b1001 %
b1001 1
b1001 W
b1000 $
b1000 0
b1000 S
b110 #
b110 /
b110 O
#155
b10000010 :
b10000010 E
b10000010 u
b1100011 ;
b1100011 F
b1100011 q
b1001000 <
b1001000 G
b1001000 m
b11100 =
b11100 H
b11100 i
b10100 ?
b10100 J
b10100 a
b100000 @
b100000 K
b100000 ]
b11011 A
b11011 L
b11011 Y
b10000 B
b10000 M
b10000 U
b111000000 !
b111000000 9
b111000000 D
b110 C
b110 N
b110 Q
1"
#160
0"
b10000 .
b101111100 -
b1001 ,
b1001 8
b1001 s
b111 +
b111 7
b111 o
b100 *
b100 6
b100 k
b110 )
b110 5
b110 g
b101 (
b101 4
b101 c
b110 '
b110 3
b110 _
b1010 &
b1010 2
b1010 [
b110 %
b110 1
b110 W
b1101 $
b1101 0
b1101 S
b1001 #
b1001 /
b1001 O
#165
b1001 C
b1001 N
b1001 Q
b11010 B
b11010 M
b11010 U
b10010 A
b10010 L
b10010 Y
b101000 @
b101000 K
b101000 ]
b11110 ?
b11110 J
b11110 a
b11110 >
b11110 I
b11110 e
b101010 =
b101010 H
b101010 i
b100000 <
b100000 G
b100000 m
b111111 ;
b111111 F
b111111 q
b101111100 !
b101111100 9
b101111100 D
b1011010 :
b1011010 E
b1011010 u
1"
#170
0"
b10001 .
b1000111110 -
b1101 +
b1101 7
b1101 o
b1100 *
b1100 6
b1100 k
b1000 )
b1000 5
b1000 g
b1110 (
b1110 4
b1110 c
b111 '
b111 3
b111 _
b1101 &
b1101 2
b1101 [
b1000 %
b1000 1
b1000 W
b1000 $
b1000 0
b1000 S
b100 #
b100 /
b100 O
#175
b1110101 ;
b1110101 F
b1110101 q
b1100000 <
b1100000 G
b1100000 m
b111000 =
b111000 H
b111000 i
b1010100 >
b1010100 I
b1010100 e
b100011 ?
b100011 J
b100011 a
b110100 @
b110100 K
b110100 ]
b11000 A
b11000 L
b11000 Y
b10000 B
b10000 M
b10000 U
b1000111110 !
b1000111110 9
b1000111110 D
b100 C
b100 N
b100 Q
1"
#180
0"
b10010 .
b111001111 -
b1010 ,
b1010 8
b1010 s
b1110 +
b1110 7
b1110 o
b1010 *
b1010 6
b1010 k
b11 )
b11 5
b11 g
b0 (
b0 4
b0 c
b110 '
b110 3
b110 _
b1010 %
b1010 1
b1010 W
b110 $
b110 0
b110 S
b1100 #
b1100 /
b1100 O
#185
b1100 C
b1100 N
b1100 Q
b1100 B
b1100 M
b1100 U
b11110 A
b11110 L
b11110 Y
b11110 ?
b11110 J
b11110 a
b0 >
b0 I
b0 e
b10101 =
b10101 H
b10101 i
b1010000 <
b1010000 G
b1010000 m
b1111110 ;
b1111110 F
b1111110 q
b111001111 !
b111001111 9
b111001111 D
b1100100 :
b1100100 E
b1100100 u
1"
#190
0"
b10011 .
b110110101 -
b1100 ,
b1100 8
b1100 s
b1101 +
b1101 7
b1101 o
b110 *
b110 6
b110 k
b110 )
b110 5
b110 g
b111 &
b111 2
b111 [
b1001 %
b1001 1
b1001 W
b1010 $
b1010 0
b1010 S
b101 #
b101 /
b101 O
#195
b1111000 :
b1111000 E
b1111000 u
b1110101 ;
b1110101 F
b1110101 q
b110000 <
b110000 G
b110000 m
b101010 =
b101010 H
b101010 i
b11100 @
b11100 K
b11100 ]
b11011 A
b11011 L
b11011 Y
b10100 B
b10100 M
b10100 U
b110110101 !
b110110101 9
b110110101 D
b101 C
b101 N
b101 Q
1"
